__init__.py
estadisticos.py
paquete_proyecto_2_dl-0.0.1.dist-info/LICENSE
paquete_proyecto_2_dl-0.0.1.dist-info/METADATA
paquete_proyecto_2_dl-0.0.1.dist-info/WHEEL
paquete_proyecto_2_dl-0.0.1.dist-info/top_level.txt
paquete_proyecto_2_dl-0.0.1.dist-info/RECORD
