Metadata-Version: 2.1
Name: paquete-proyecto-2-dl
Version: 0.0.1
Summary: paquete del proyecto 2
Author-email: Damian Leon <damianleon@usantotomas.edu.co>
License: MIT License        
Project-URL: Homepage, https://github.com/IanDam/paquete_proyecto_2_dl
Project-URL: Bug Tracker, https://github.com/IanDam/paquete_proyecto_2_dl/issues
Classifier: Programming Language :: Python :: 3
Classifier: License :: OSI Approved :: MIT License
Classifier: Operating System :: OS Independent
Requires-Python: >=3.7
License-File: LICENSE
